labbicons/__init__.py
labbicons/apps.py
labbicons/cli/__init__.py
labbicons/cli/handlers/__init__.py
labbicons/cli/handlers/icons_handler.py
labbicons/cli/main.py
labbicons/metadata/remix.json
labbicons/metadata.py
labbicons/templates/cotton/lbi/index.html
labbicons/templates/cotton/lbi/rmx/24_hours.html
labbicons/templates/cotton/lbi/rmx/4k.html
labbicons/templates/cotton/lbi/rmx/a_b.html
labbicons/templates/cotton/lbi/rmx/accessibility.html
labbicons/templates/cotton/lbi/rmx/account_box.html
labbicons/templates/cotton/lbi/rmx/account_box_2.html
labbicons/templates/cotton/lbi/rmx/account_circle.html
labbicons/templates/cotton/lbi/rmx/account_circle_2.html
labbicons/templates/cotton/lbi/rmx/account_pin_box.html
labbicons/templates/cotton/lbi/rmx/account_pin_circle.html
labbicons/templates/cotton/lbi/rmx/add.html
labbicons/templates/cotton/lbi/rmx/add_box.html
labbicons/templates/cotton/lbi/rmx/add_circle.html
labbicons/templates/cotton/lbi/rmx/add_large.html
labbicons/templates/cotton/lbi/rmx/admin.html
labbicons/templates/cotton/lbi/rmx/advertisement.html
labbicons/templates/cotton/lbi/rmx/aed.html
labbicons/templates/cotton/lbi/rmx/aed_electrodes.html
labbicons/templates/cotton/lbi/rmx/ai_generate.html
labbicons/templates/cotton/lbi/rmx/ai_generate_2.html
labbicons/templates/cotton/lbi/rmx/ai_generate_text.html
labbicons/templates/cotton/lbi/rmx/airplay.html
labbicons/templates/cotton/lbi/rmx/alarm.html
labbicons/templates/cotton/lbi/rmx/alarm_add.html
labbicons/templates/cotton/lbi/rmx/alarm_snooze.html
labbicons/templates/cotton/lbi/rmx/alarm_warning.html
labbicons/templates/cotton/lbi/rmx/album.html
labbicons/templates/cotton/lbi/rmx/alert.html
labbicons/templates/cotton/lbi/rmx/alibaba_cloud.html
labbicons/templates/cotton/lbi/rmx/aliens.html
labbicons/templates/cotton/lbi/rmx/align_bottom.html
labbicons/templates/cotton/lbi/rmx/align_center.html
labbicons/templates/cotton/lbi/rmx/align_item_bottom.html
labbicons-0.1.0.dist-info/METADATA
labbicons-0.1.0.dist-info/WHEEL
labbicons-0.1.0.dist-info/licenses/LICENSE
labbicons-0.1.0.dist-info/RECORD
